{
  "fluentMethods": true,
  "clientRootFolder": "",
  "relationships": [],
  "fields": [
    {
      "fieldName": "viewName",
      "fieldType": "String",
      "fieldValidateRules": []
    },
    {
      "fieldName": "description",
      "fieldType": "String",
      "fieldValidateRules": ["required", "maxlength"],
      "fieldValidateRulesMaxlength": "100"
    },
    {
      "fieldName": "createdBy",
      "fieldType": "String"
    },
    {
      "fieldName": "lastModifiedBy",
      "fieldType": "String"
    },
    {
      "fieldName": "lastModifiedDate",
      "fieldType": "LocalDate"
    },
    {
      "fieldName": "published",
      "fieldType": "Boolean"
    },
    {
      "fieldName": "image",
      "fieldType": "byte[]",
      "fieldTypeBlobContent": "image"
    },
    {
      "fieldName": "viewDashboard",
      "fieldType": "String"
    }
  ],
  "dto": "no",
  "searchEngine": false,
  "service": "no",
  "entityTableName": "views",
  "databaseType": "postgres",
  "readOnly": false,
  "jpaMetamodelFiltering": false,
  "pagination": "no"
}
